sentry_tunnel/__init__.py
sentry_tunnel/apps.py
sentry_tunnel/urls.py
sentry_tunnel/views.py
ngits_drf_sentry_tunnel-1.0.0.dist-info/METADATA
ngits_drf_sentry_tunnel-1.0.0.dist-info/WHEEL
ngits_drf_sentry_tunnel-1.0.0.dist-info/top_level.txt
ngits_drf_sentry_tunnel-1.0.0.dist-info/RECORD
