Metadata-Version: 2.1
Name: ngits-drf-sentry-tunnel
Version: 1.0.0
Summary: Sentry tunnel for DRF
Home-page: https://ngits.dev
Author: NGITs
License: BSD-3-Clause
Classifier: Environment :: Web Environment
Classifier: Framework :: Django
Classifier: Framework :: Django :: 4.0
Classifier: Intended Audience :: Developers
Classifier: License :: OSI Approved :: BSD License
Classifier: Operating System :: OS Independent
Classifier: Programming Language :: Python :: 3.9
Classifier: Topic :: Internet :: WWW/HTTP
Classifier: Topic :: Internet :: WWW/HTTP :: Dynamic Content
Requires-Python: >=3.9
Requires-Dist: Django (==4.*)
Requires-Dist: djangorestframework (==3.*)
Requires-Dist: requests (==2.*)
